tsingrocpymeteo/__init__.py
tsingrocpymeteo/auth.py
tsingrocpymeteo/meteo.py
tsingroc_pymeteo-0.2.0.dist-info/METADATA
tsingroc_pymeteo-0.2.0.dist-info/WHEEL
tsingroc_pymeteo-0.2.0.dist-info/RECORD
